[
  {
    "id": "00ulthapbErVUwVJt48x7",
    "profile_id": "00ulthapbErVUwVJy4x6",
    "name": "Kole Hane",
    "email": "llama001@maildrop.cc",
    "phone": "(800) 275-8777",
    "avatarUrl": "https://s3.amazonaws.com/uifaces/faces/twitter/besbujupi/128.jpg",
    "address": "US Post Office Midtown, 223 West 38th Street, New York, NY 10018, United States of America",
    "city": "New York",
    "state": "NY",
    "zip_code": 10018,
    "latitude": 40.7541404,
    "longitude": -73.9898612,
    "country": "United States",
    "travel": true,
    "travel_distance": 50,
    "bio": null,
    "created_at": "2020-11-03T06:37:10.931Z",
    "services": [
      {
        "id": "9byr1zbnz3vzuqj5y97h",
        "serviceId": "11ulthapbErVUwVJt58x0",
        "name": "Bath & Full Haircut",
        "description": "Omnis nihil consectetur voluptatem similique voluptas.",
        "cost": 19.99,
        "service_hours": "Mon-Fri 9am - 5pm",
        "created_at": "2020-11-03T06:37:11.008Z",
        "updated_at": "2020-11-03T06:37:11.008Z"
      },
      {
        "id": "hyhdyusoaQOIIKJDS-PO",
        "serviceId": "service2_id",
        "name": "Full Grooming",
        "description": "Voluptatem delectus accusantium cumque reprehenderit numquam ut omnis et et.",
        "cost": 80,
        "service_hours": "Mon-Fri 9am-5pm",
        "created_at": "2020-11-08T18:50:58.742Z",
        "updated_at": "2020-11-08T18:50:58.742Z"
      },
      {
        "id": "asdcyusoaQOIIKJDS-PO",
        "serviceId": "service3_id",
        "name": "Partial Grooming",
        "description": "Omnis incidunt omnis voluptatem aliquid.",
        "cost": 49.99,
        "service_hours": "Mon-Fri 9am-5pm",
        "created_at": "2020-11-08T18:51:22.421Z",
        "updated_at": "2020-11-08T18:51:22.421Z"
      },
      {
        "id": "qweryusoaQOIIKJDS-PO",
        "serviceId": "service4_id",
        "name": "Teeth Cleaning",
        "description": "Eius quas qui nostrum.",
        "cost": 25,
        "service_hours": "Mon-Fri 9am-5pm",
        "created_at": "2020-11-08T18:51:40.621Z",
        "updated_at": "2020-11-08T18:51:40.621Z"
      },
      {
        "id": "optrusoaQOIIKJDS-JA",
        "serviceId": "service5_id",
        "name": "Nail Trimming",
        "description": "Similique et assumenda.",
        "cost": 20.99,
        "service_hours": "Mon-Fri 9am-5pm",
        "created_at": "2020-11-08T18:52:04.933Z",
        "updated_at": "2020-11-08T18:52:04.933Z"
      },
      {
        "id": "yuikpusoaQOIIKJDS-YU",
        "serviceId": "service6_id",
        "name": "Ear Cleaning",
        "description": "Illum minima nostrum sunt id magni.",
        "cost": 15,
        "service_hours": "Mon-Fri 9am-5pm",
        "created_at": "2020-11-08T18:52:26.326Z",
        "updated_at": "2020-11-08T18:52:26.326Z"
      }
    ],
    "appointments": [
      {
        "id": "26aff196-b982-4307-b8d2-d8f51b33931e",
        "clientId": "user7_id",
        "clientName": "Martin Mark",
        "groomerId": "00ulthapbErVUwVJy4x6",
        "animalId": "animal1_id",
        "animalType": "dog",
        "animalBreed": "bulldog",
        "location": "Mebane NC",
        "appointmentDate": "2020-11-19T08:20:00.000Z",
        "createdAt": "2020-11-11T00:43:20.184Z",
        "groomerName": "Kole Hane",
        "groomerEmail": "llama001@maildrop.cc",
        "services": [
          {
            "name": "Full Grooming",
            "cost": 80
          },
          {
            "name": "Partial Grooming",
            "cost": 49.99
          },
          {
            "name": "Teeth Cleaning",
            "cost": 25
          }
        ]
      }
    ],
    "ratings": 4.9,
    "ratingCount": 3
  },
  {
    "id": "profile2_id",
    "profile_id": "user2_id",
    "name": "Lucas King",
    "email": "llama002@maildrop.cc",
    "phone": "(800) 275-8777",
    "avatarUrl": "https://s3.amazonaws.com/uifaces/faces/twitter/thatonetommy/128.jpg",
    "address": "1300 Evans Avenue, San Francisco, CA 94124, United States of America",
    "city": "San Francisco",
    "state": "CA",
    "zip_code": 94124,
    "latitude": 37.739718,
    "longitude": -122.3829295,
    "country": "United States",
    "travel": false,
    "travel_distance": 0,
    "bio": null,
    "created_at": "2020-11-03T06:37:10.931Z",
    "services": [],
    "appointments": [],
    "ratings": 0,
    "ratingCount": 0
  },
  {
    "id": "profile3_id",
    "profile_id": "user3_id",
    "name": "Garland Baumbach",
    "email": "llama003@maildrop.cc",
    "phone": "(800) 275-8000",
    "avatarUrl": "https://s3.amazonaws.com/uifaces/faces/twitter/tereshenkov/128.jpg",
    "address": "James A Farley Post Office, 421 8th Avenue, New York, NY 10001, United States of America",
    "city": "New York",
    "state": "NY",
    "zip_code": 10001,
    "latitude": 40.7515183,
    "longitude": -73.9958264,
    "country": "United States",
    "travel": false,
    "travel_distance": 0,
    "bio": null,
    "created_at": "2020-11-03T06:37:10.931Z",
    "services": [],
    "appointments": [],
    "ratings": 0,
    "ratingCount": 0
  },
  {
    "id": "profile4_id",
    "profile_id": "user4_id",
    "name": "Arvel Bernier",
    "email": "llama004@maildrop.cc",
    "phone": "(800) 555-7790",
    "avatarUrl": "https://s3.amazonaws.com/uifaces/faces/twitter/richardgarretts/128.jpg",
    "address": "335 East 14th Street, New York, NY 11226, United States of America",
    "city": "New York",
    "state": "NY",
    "zip_code": 11226,
    "latitude": 40.6415183,
    "longitude": -73.9653234,
    "country": "United States",
    "travel": true,
    "travel_distance": 20,
    "bio": null,
    "created_at": "2020-11-03T06:37:10.931Z",
    "services": [],
    "appointments": [],
    "ratings": 0,
    "ratingCount": 0
  },
  {
    "id": "profile5_id",
    "profile_id": "user5_id",
    "name": "Max Goldner",
    "email": "llama005@maildrop.cc",
    "phone": "(800) 305-4400",
    "avatarUrl": "https://s3.amazonaws.com/uifaces/faces/twitter/wiljanslofstra/128.jpg",
    "address": "1400 Pine Street, San Francisco, CA 94109, United States of America",
    "city": "San Francisco",
    "state": "CA",
    "zip_code": 94109,
    "latitude": 37.789892,
    "longitude": -122.419013,
    "country": "United States",
    "travel": false,
    "travel_distance": 0,
    "bio": null,
    "created_at": "2020-11-03T06:37:10.931Z",
    "services": [],
    "appointments": [],
    "ratings": 0,
    "ratingCount": 0
  },
  {
    "id": "profile6_id",
    "profile_id": "user6_id",
    "name": "Tim Leon",
    "email": "llama006@maildrop.cc",
    "phone": "",
    "avatarUrl": "https://s3.amazonaws.com/uifaces/faces/twitter/picard102/128.jpg",
    "address": "Hallidie Building, 130-150 Sutter Street, San Francisco, CA 94108, United States of America",
    "city": "San Francisco",
    "state": "CA",
    "zip_code": 94108,
    "latitude": 37.7902124,
    "longitude": -122.403054,
    "country": "United States",
    "travel": true,
    "travel_distance": 30,
    "bio": null,
    "created_at": "2020-11-03T06:37:10.931Z",
    "services": [],
    "appointments": [],
    "ratings": 0,
    "ratingCount": 0
  }
]